prefect_dbt/__init__.py
prefect_dbt/_version.py
prefect_dbt/utilities.py
prefect_dbt/cli/__init__.py
prefect_dbt/cli/commands.py
prefect_dbt/cli/credentials.py
prefect_dbt/cli/configs/__init__.py
prefect_dbt/cli/configs/base.py
prefect_dbt/cli/configs/bigquery.py
prefect_dbt/cli/configs/postgres.py
prefect_dbt/cli/configs/snowflake.py
prefect_dbt/cloud/__init__.py
prefect_dbt/cloud/clients.py
prefect_dbt/cloud/credentials.py
prefect_dbt/cloud/exceptions.py
prefect_dbt/cloud/jobs.py
prefect_dbt/cloud/models.py
prefect_dbt/cloud/runs.py
prefect_dbt/cloud/utils.py
prefect_dbt/core/__init__.py
prefect_dbt/core/_tracker.py
prefect_dbt/core/runner.py
prefect_dbt/core/settings.py
prefect_dbt-0.7.16.dist-info/licenses/LICENSE
prefect_dbt-0.7.16.dist-info/METADATA
prefect_dbt-0.7.16.dist-info/WHEEL
prefect_dbt-0.7.16.dist-info/entry_points.txt
prefect_dbt-0.7.16.dist-info/top_level.txt
prefect_dbt-0.7.16.dist-info/RECORD
